togglreports/__init__.py
togglreports/build.py
togglreports/cli_parser.py
togglreports/config.py
togglreports/main.py
togglreports/py.typed
togglreports/togglapi.py
togglreports/utils.py
togglreports/core/__init__.py
togglreports/core/app.py
togglreports/core/plugin_loader.py
togglreports/core/protocols.py
togglreports/core/report_factory.py
togglreports/data/reports.json
togglreports/data/reports_example.json
togglreports/plugins/__init__.py
togglreports/plugins/example.py
togglreports/plugins/sgu.py
togglreports-2.6.0.dist-info/LICENSE
togglreports-2.6.0.dist-info/METADATA
togglreports-2.6.0.dist-info/WHEEL
togglreports-2.6.0.dist-info/entry_points.txt
togglreports-2.6.0.dist-info/top_level.txt
togglreports-2.6.0.dist-info/RECORD
