Metadata-Version: 2.1
Name: togglreports
Version: 2.6.0
Summary: A simple project to automate the creation of reports using the Toggl API.
Home-page: https://github.com/ro-56/togglReports
Author: Rodrigo Mendonça
Author-email: rodrigogr.mendonca@gmail.com
License: UNKNOWN
Platform: UNKNOWN
Classifier: Development Status :: 5 - Production/Stable
Classifier: Intended Audience :: Developers
Classifier: License :: OSI Approved :: MIT License
Classifier: Programming Language :: Python :: 3
Classifier: Programming Language :: Python :: 3 :: Only
Requires-Python: >=3.9
License-File: LICENSE
Requires-Dist: pandas (==1.5.3)
Requires-Dist: pyyaml (==6.0)
Requires-Dist: requests (==2.28.2)
Requires-Dist: argparse (==1.4.0)
Requires-Dist: configparser (==5.2.0)
